DGNER/__init__.py
DGNER/dategen.py
DateGenerator-0.0.2.dist-info/LICENSE.txt
DateGenerator-0.0.2.dist-info/METADATA
DateGenerator-0.0.2.dist-info/WHEEL
DateGenerator-0.0.2.dist-info/top_level.txt
DateGenerator-0.0.2.dist-info/RECORD
